beastx/__init__.py
beastx/__main__.py
BeastX-3.0.dist-info/LICENSE
BeastX-3.0.dist-info/METADATA
BeastX-3.0.dist-info/WHEEL
BeastX-3.0.dist-info/top_level.txt
BeastX-3.0.dist-info/RECORD
