Metadata-Version: 2.1
Name: BeastX
Version: 3.0
Summary: A Python Package 
Home-page: https://github.com/msy1717
Author: @Godmrunal
Author-email: mrunalgaming7@gmail.com
License: UNKNOWN
Platform: UNKNOWN
Classifier: Programming Language :: Python :: 3
Classifier: License :: OSI Approved :: MIT License
Classifier: Operating System :: OS Independent
Requires-Python: >=3.6
